setup.py
discount/__init__.py
discount/cart_modifiers.py
discount/managers.py
discount/mixins.py
discount/models.py
discount/urls.py
discount/views.py
discount/default_discounts/__init__.py
discount/default_discounts/admin.py
discount/default_discounts/models.py
discount/tests/__init__.py
discount/tests/base.py
discount/tests/view_tests.py
django_shop_discounts.egg-info/PKG-INFO
django_shop_discounts.egg-info/SOURCES.txt
django_shop_discounts.egg-info/dependency_links.txt
django_shop_discounts.egg-info/requires.txt
django_shop_discounts.egg-info/top_level.txt