Metadata-Version: 1.0
Name: django-shop-discounts
Version: 0.0.7
Summary: configurable and extendible discount app for Django-shop
Home-page: https://github.com/bmihelac/django-shop-discounts
Author: Bojan Mihelac
Author-email: bmihelac@mihelac.org
License: BSD License
Platform: UNKNOWN
